{"id":"jnzzmcm","name":"m6y","gamePosition":{"cells":[{"x":0,"y":0,"player":"player-1","moveId":1},{"x":0,"y":4,"player":"player-2","moveId":2},{"x":1,"y":3,"player":"player-2","moveId":3},{"x":1,"y":0,"player":"player-1","moveId":4},{"x":-1,"y":1,"player":"player-1","moveId":5},{"x":-1,"y":0,"player":"player-2","moveId":6},{"x":1,"y":-1,"player":"player-2","moveId":7},{"x":-1,"y":5,"player":"player-1","moveId":8},{"x":0,"y":3,"player":"player-1","moveId":9},{"x":2,"y":2,"player":"player-2","moveId":10},{"x":3,"y":1,"player":"player-2","moveId":11},{"x":4,"y":0,"player":"player-1","moveId":12},{"x":4,"y":1,"player":"player-1","moveId":13},{"x":3,"y":0,"player":"player-2","moveId":14},{"x":4,"y":2,"player":"player-2","moveId":15},{"x":3,"y":2,"player":"player-1","moveId":16},{"x":2,"y":3,"player":"player-1","moveId":17},{"x":1,"y":4,"player":"player-2","moveId":18},{"x":-1,"y":4,"player":"player-2","moveId":19},{"x":2,"y":4,"player":"player-1","moveId":20},{"x":1,"y":5,"player":"player-1","moveId":21},{"x":3,"y":3,"player":"player-2","moveId":22},{"x":4,"y":-2,"player":"player-2","moveId":23},{"x":4,"y":-1,"player":"player-1","moveId":24},{"x":5,"y":-3,"player":"player-1","moveId":25},{"x":6,"y":-3,"player":"player-2","moveId":26},{"x":5,"y":-4,"player":"player-2","moveId":27},{"x":4,"y":-3,"player":"player-1","moveId":28},{"x":6,"y":-4,"player":"player-1","moveId":29},{"x":5,"y":-5,"player":"player-2","moveId":30},{"x":7,"y":-6,"player":"player-2","moveId":31},{"x":6,"y":-5,"player":"player-1","moveId":32},{"x":7,"y":-7,"player":"player-1","moveId":33},{"x":6,"y":-7,"player":"player-2","moveId":34},{"x":6,"y":-8,"player":"player-2","moveId":35},{"x":5,"y":-7,"player":"player-1","moveId":36},{"x":4,"y":-6,"player":"player-1","moveId":37},{"x":4,"y":-7,"player":"player-2","moveId":38},{"x":3,"y":5,"player":"player-2","moveId":39},{"x":3,"y":7,"player":"player-1","moveId":40},{"x":2,"y":8,"player":"player-1","moveId":41},{"x":4,"y":6,"player":"player-2","moveId":42},{"x":2,"y":9,"player":"player-2","moveId":43},{"x":-3,"y":9,"player":"player-1","moveId":44},{"x":-4,"y":9,"player":"player-1","moveId":45},{"x":-1,"y":7,"player":"player-2","moveId":46},{"x":-2,"y":9,"player":"player-2","moveId":47},{"x":-2,"y":10,"player":"player-1","moveId":48},{"x":-4,"y":11,"player":"player-1","moveId":49},{"x":-3,"y":10,"player":"player-2","moveId":50},{"x":-4,"y":10,"player":"player-2","moveId":51},{"x":-8,"y":8,"player":"player-1","moveId":52},{"x":-8,"y":7,"player":"player-1","moveId":53},{"x":-7,"y":6,"player":"player-2","moveId":54},{"x":-8,"y":5,"player":"player-2","moveId":55},{"x":-8,"y":6,"player":"player-1","moveId":56},{"x":-7,"y":5,"player":"player-1","moveId":57},{"x":-9,"y":7,"player":"player-2","moveId":58},{"x":-5,"y":10,"player":"player-2","moveId":59},{"x":-9,"y":6,"player":"player-1","moveId":60},{"x":7,"y":-4,"player":"player-1","moveId":61},{"x":-3,"y":3,"player":"player-2","moveId":62},{"x":8,"y":-4,"player":"player-2","moveId":63},{"x":-5,"y":9,"player":"player-1","moveId":64},{"x":-6,"y":10,"player":"player-1","moveId":65},{"x":-8,"y":9,"player":"player-2","moveId":66},{"x":-6,"y":11,"player":"player-2","moveId":67}],"currentTurnPlayer":"player-1","placementsRemaining":2}}